odoo/addons/l10n_th_gov_hr_expense/README.rst
odoo/addons/l10n_th_gov_hr_expense/__init__.py
odoo/addons/l10n_th_gov_hr_expense/__manifest__.py
odoo/addons/l10n_th_gov_hr_expense/i18n/l10n_th_gov_hr_expense.pot
odoo/addons/l10n_th_gov_hr_expense/models/__init__.py
odoo/addons/l10n_th_gov_hr_expense/models/account_move.py
odoo/addons/l10n_th_gov_hr_expense/models/hr_expense.py
odoo/addons/l10n_th_gov_hr_expense/models/purchase_request.py
odoo/addons/l10n_th_gov_hr_expense/readme/CONFIGURE.rst
odoo/addons/l10n_th_gov_hr_expense/readme/CONTRIBUTORS.rst
odoo/addons/l10n_th_gov_hr_expense/readme/DESCRIPTION.rst
odoo/addons/l10n_th_gov_hr_expense/security/ir.model.access.csv
odoo/addons/l10n_th_gov_hr_expense/static/description/icon.png
odoo/addons/l10n_th_gov_hr_expense/static/description/index.html
odoo/addons/l10n_th_gov_hr_expense/tests/__init__.py
odoo/addons/l10n_th_gov_hr_expense/tests/test_gov_hr_expense.py
odoo/addons/l10n_th_gov_hr_expense/views/account_move_views.xml
odoo/addons/l10n_th_gov_hr_expense/views/hr_expense_views.xml
odoo/addons/l10n_th_gov_hr_expense/views/purchase_request_views.xml
odoo/addons/l10n_th_gov_hr_expense/views/reminder_definition_view.xml
odoo_addon_l10n_th_gov_hr_expense-15.0.1.2.2.dist-info/METADATA
odoo_addon_l10n_th_gov_hr_expense-15.0.1.2.2.dist-info/WHEEL
odoo_addon_l10n_th_gov_hr_expense-15.0.1.2.2.dist-info/top_level.txt
odoo_addon_l10n_th_gov_hr_expense-15.0.1.2.2.dist-info/RECORD
