Metadata-Version: 2.1
Name: odoo-addon-l10n_th_gov_hr_expense
Version: 15.0.1.2.2
Summary: Thai Localization - Government Expense
Home-page: https://github.com/OCA/l10n-thailand
Author: Ecosoft, Odoo Community Association (OCA)
Author-email: support@odoo-community.org
License: AGPL-3
Classifier: Programming Language :: Python
Classifier: Framework :: Odoo
Classifier: Framework :: Odoo :: 15.0
Classifier: License :: OSI Approved :: GNU Affero General Public License v3
Classifier: Development Status :: 3 - Alpha
Requires-Python: >=3.8
Requires-Dist: odoo-addon-hr-expense-advance-clearing<15.1dev,>=15.0dev
Requires-Dist: odoo-addon-hr-expense-advance-overdue-reminder<15.1dev,>=15.0dev
Requires-Dist: odoo-addon-l10n-th-gov-purchase-request<15.1dev,>=15.0dev
Requires-Dist: odoo<15.1dev,>=15.0a
